MANIFEST.in
README.rst
setup.py
dictances/__init__.py
dictances/__version__.py
dictances/bhattacharyya.py
dictances/canberra.py
dictances/chebyshev.py
dictances/chi_square.py
dictances/cosine.py
dictances/distances_utils.py
dictances/euclidean.py
dictances/hamming.py
dictances/intersection_nth_variation.py
dictances/intersection_squared_hellinger.py
dictances/intersection_squared_variation.py
dictances/intersection_total_variation.py
dictances/jensen_shannon.py
dictances/kullback_leibler.py
dictances/mae.py
dictances/minkowsky.py
dictances/mse.py
dictances/normal_chi_square.py
dictances/nth_variation.py
dictances/pearson.py
dictances/squared_variation.py
dictances/total_variation.py
dictances.egg-info/PKG-INFO
dictances.egg-info/SOURCES.txt
dictances.egg-info/dependency_links.txt
dictances.egg-info/requires.txt
dictances.egg-info/top_level.txt