Metadata-Version: 2.1
Name: dictances
Version: 1.5.2
Summary: Distances and divergences between distributions implemented in python.
Home-page: https://github.com/LucaCappelletti94/dictances
Author: Luca Cappelletti
Author-email: cappelletti.luca94@gmail.com
License: MIT
Platform: UNKNOWN
Classifier: Development Status :: 3 - Alpha
Classifier: License :: OSI Approved :: MIT License
Classifier: Programming Language :: Python :: 3
Provides-Extra: test
